{
 "coc.preferences.formatOnSaveFiletypes": ["css", "markdown", "javascript", "graphql", "html", "yaml",  "json", "python"],

  // python config
  "python.linting.enabled": true,
  "python.linting.pylintEnabled": true,

  "snippets.ultisnips.directories":
  [
    "UltiSnips",
    "~/.config/nvim/utils/snips"
  ],

  // JavaScript
  "languageserver": {
    "go": {
      "command": "gopls",
      "rootPatterns": ["go.mod"],
      "trace.server": "verbose",
      "filetypes": ["go"]
    }
  },
  
  //java
  "codeLens.enable": true,
  "java.referencesCodeLens.enabled": true,
  "java.jdt.ls.vmargs": "-javaagent:/usr/local/share/lombok/lombok.jar"

  //html
  

}
